apmto/__init__.py
apmto/apmto.py
apmto/image.py
apmto/video.py
apmto-1.0.0.dist-info/LICENSE
apmto-1.0.0.dist-info/METADATA
apmto-1.0.0.dist-info/WHEEL
apmto-1.0.0.dist-info/top_level.txt
apmto-1.0.0.dist-info/RECORD
