Metadata-Version: 2.1
Name: apmto
Version: 1.0.0
Summary: Simple python package wrapper for converting apple media formatted files into high-compatible formats.
Home-page: https://github.com/nda111/APMTO
Author: Geunhyeok Yu
Author-email: geunhyeok0111@gmail.com
Classifier: Programming Language :: Python :: 3
Classifier: License :: OSI Approved :: MIT License
Classifier: Operating System :: OS Independent
Requires-Python: >=3.9
License-File: LICENSE
Requires-Dist: colorama
Requires-Dist: ffmpeg-python
Requires-Dist: future
Requires-Dist: numpy
Requires-Dist: pillow
Requires-Dist: pillow-heif
